{
  "bindungssehnsucht-normal.md": [
    "checklist-bindung-sicherheit",
    "checklist-leere-verschmelzung",
    "checkliste_sog_hingabe"
  ],
  "das-erste-mal.md": [
    "checklist-bindung-sicherheit",
    "checklist-leere-verschmelzung",
    "checkliste_sog_hingabe"
  ],
  "der-sichere-hafen.md": [
    "checklist-passivitaet",
    "checklist-besitz"
  ],
  "emotionale-leere.md": [
    "checklist-bindung-sicherheit",
    "checklist-leere-verschmelzung",
    "checkliste_sog_hingabe"
  ],
  "erschoepft-vom-stark-sein.md": [
    "checklist-bindung-sicherheit",
    "checklist-leere-verschmelzung",
    "checkliste_sog_hingabe"
  ],
  "ich-will-einfach-gehalten-werden.md": [
    "checklist-bindung-sicherheit",
    "checklist-leere-verschmelzung",
    "checkliste_sog_hingabe"
  ],
  "kontrolle-abgeben.md": [
    "checklist-bindung-sicherheit",
    "checklist-leere-verschmelzung",
    "checkliste_sog_hingabe"
  ],
  "sehnsucht-nach-hingabe.md": [
    "checklist-passivitaet",
    "checklist-besitz"
  ],
  "zu-viel-liebe-zu-wenig-liebe.md": [
    "checklist-bindung-sicherheit",
    "checklist-leere-verschmelzung",
    "checkliste_sog_hingabe"
  ]
}